stream_tui/__init__.py
stream_tui/bb_parser.py
stream_tui/most.py
stream_tui-0.7.1.dist-info/METADATA
stream_tui-0.7.1.dist-info/WHEEL
stream_tui-0.7.1.dist-info/RECORD
