Metadata-Version: 2.1
Name: stream-tui
Version: 0.7.1
Summary: Easily create pretty user interfaces for your CLI apps
Author: Jakob Pinterits
Author-email: jakob.pinterits@gmail.com
Requires-Python: >=3.9,<4.0
Classifier: Programming Language :: Python :: 3
Classifier: Programming Language :: Python :: 3.9
Classifier: Programming Language :: Python :: 3.10
Classifier: Programming Language :: Python :: 3.11
Requires-Dist: blessed (>=1.19.1,<2.0.0)
Requires-Dist: colorama (>=0.4.6,<0.5.0)
Requires-Dist: readchar (>=4.0.3,<5.0.0)
